{
  "understanding": {
    "C": "Phase2 P2-2 (Hello KService READY=True) に関する記述を、指定の2種の source_texts（STATE/current_state.md の該当セクション、および P2-2 を扱う Issue/PR の本文）だけを根拠として、v1 ルール（segmenter mode）に従い info_node と info_relation に分解する。最大ノード数は20。新規の内容や創作は禁止。",
    "G": "",
    "delta": "",
    "assumptions": [],
    "unknowns": []
  },
  "plan": [],
  "acceptance": [
    "受領。source_texts の原文（該当セクション抜粋と Issue/PR 本文）をご提供ください。受領次第、v1ルールに従って最大20ノードで info_node/info_relation を作成します。"
  ],
  "context_header": "repo=vpm-mini / branch=main / phase=Phase 2",
  "typing": "plan要約",
  "confidence": 0.5,
  "citations": []
}
